{"mlbPlayerId":687637,"playerName":"Dylan Beavers","lastUpdated":"2026-07-13T20:28:17.658Z","age":24,"birthPlace":"San Luis Obispo, CA, USA","preProPath":"California","statGroups":[{"title":"2026 Season Line","source":"MLB Stats API","stats":[{"label":"G","value":"43"},{"label":"PA","value":"148"},{"label":"AVG","value":".233"},{"label":"OBP","value":".320"},{"label":"SLG","value":".349"},{"label":"OPS","value":".669"},{"label":"HR","value":"2"},{"label":"RBI","value":"13"},{"label":"SB","value":"3"}]},{"title":"Career Line","source":"MLB Stats API","stats":[{"label":"G","value":"78"},{"label":"PA","value":"285"},{"label":"AVG","value":".230"},{"label":"OBP","value":".346"},{"label":"SLG","value":".372"},{"label":"OPS","value":".718"},{"label":"HR","value":"6"},{"label":"RBI","value":"27"},{"label":"SB","value":"5"}]}],"statHistory":{"type":"hitter","source":"MLB Stats API","seasons":[{"season":"2025","team":"Baltimore Orioles","level":"MLB","stats":[{"label":"G","value":"35"},{"label":"PA","value":"137"},{"label":"AVG","value":".227"},{"label":"OBP","value":".375"},{"label":"SLG","value":".400"},{"label":"OPS","value":".775"},{"label":"HR","value":"4"},{"label":"RBI","value":"14"},{"label":"SB","value":"2"}]},{"season":"2026","team":"Baltimore Orioles","level":"MLB","stats":[{"label":"G","value":"43"},{"label":"PA","value":"148"},{"label":"AVG","value":".233"},{"label":"OBP","value":".320"},{"label":"SLG","value":".349"},{"label":"OPS","value":".669"},{"label":"HR","value":"2"},{"label":"RBI","value":"13"},{"label":"SB","value":"3"}]}],"months":[{"season":"Mar 2026","team":"Baltimore Orioles","level":"MLB","stats":[{"label":"G","value":"3"},{"label":"PA","value":"9"},{"label":"AVG","value":".111"},{"label":"OBP","value":".111"},{"label":"SLG","value":".222"},{"label":"OPS","value":".333"},{"label":"HR","value":"0"},{"label":"RBI","value":"2"},{"label":"SB","value":"0"}]},{"season":"Apr 2026","team":"Baltimore Orioles","level":"MLB","stats":[{"label":"G","value":"21"},{"label":"PA","value":"81"},{"label":"AVG","value":".243"},{"label":"OBP","value":".325"},{"label":"SLG","value":".357"},{"label":"OPS","value":".682"},{"label":"HR","value":"2"},{"label":"RBI","value":"7"},{"label":"SB","value":"1"}]},{"season":"May 2026","team":"Baltimore Orioles","level":"MLB","stats":[{"label":"G","value":"9"},{"label":"PA","value":"29"},{"label":"AVG","value":".292"},{"label":"OBP","value":".414"},{"label":"SLG","value":".458"},{"label":"OPS","value":".872"},{"label":"HR","value":"0"},{"label":"RBI","value":"3"},{"label":"SB","value":"2"}]},{"season":"Jun 2026","team":"Baltimore Orioles","level":"MLB","stats":[{"label":"G","value":"3"},{"label":"PA","value":"11"},{"label":"AVG","value":".100"},{"label":"OBP","value":".182"},{"label":"SLG","value":".200"},{"label":"OPS","value":".382"},{"label":"HR","value":"0"},{"label":"RBI","value":"1"},{"label":"SB","value":"0"}]},{"season":"Jul 2026","team":"Baltimore Orioles","level":"MLB","stats":[{"label":"G","value":"7"},{"label":"PA","value":"18"},{"label":"AVG","value":".250"},{"label":"OBP","value":".333"},{"label":"SLG","value":".313"},{"label":"OPS","value":".646"},{"label":"HR","value":"0"},{"label":"RBI","value":"0"},{"label":"SB","value":"0"}]}],"splitSeries":[{"key":"all","label":"All games","seasons":[{"season":"2025","team":"Baltimore Orioles","level":"MLB","stats":[{"label":"G","value":"35"},{"label":"PA","value":"137"},{"label":"AVG","value":".227"},{"label":"OBP","value":".375"},{"label":"SLG","value":".400"},{"label":"OPS","value":".775"},{"label":"HR","value":"4"},{"label":"RBI","value":"14"},{"label":"SB","value":"2"}]},{"season":"2026","team":"Baltimore Orioles","level":"MLB","stats":[{"label":"G","value":"43"},{"label":"PA","value":"148"},{"label":"AVG","value":".233"},{"label":"OBP","value":".320"},{"label":"SLG","value":".349"},{"label":"OPS","value":".669"},{"label":"HR","value":"2"},{"label":"RBI","value":"13"},{"label":"SB","value":"3"}]}],"months":[{"season":"Mar 2026","team":"Baltimore Orioles","level":"MLB","stats":[{"label":"G","value":"3"},{"label":"PA","value":"9"},{"label":"AVG","value":".111"},{"label":"OBP","value":".111"},{"label":"SLG","value":".222"},{"label":"OPS","value":".333"},{"label":"HR","value":"0"},{"label":"RBI","value":"2"},{"label":"SB","value":"0"}]},{"season":"Apr 2026","team":"Baltimore Orioles","level":"MLB","stats":[{"label":"G","value":"21"},{"label":"PA","value":"81"},{"label":"AVG","value":".243"},{"label":"OBP","value":".325"},{"label":"SLG","value":".357"},{"label":"OPS","value":".682"},{"label":"HR","value":"2"},{"label":"RBI","value":"7"},{"label":"SB","value":"1"}]},{"season":"May 2026","team":"Baltimore Orioles","level":"MLB","stats":[{"label":"G","value":"9"},{"label":"PA","value":"29"},{"label":"AVG","value":".292"},{"label":"OBP","value":".414"},{"label":"SLG","value":".458"},{"label":"OPS","value":".872"},{"label":"HR","value":"0"},{"label":"RBI","value":"3"},{"label":"SB","value":"2"}]},{"season":"Jun 2026","team":"Baltimore Orioles","level":"MLB","stats":[{"label":"G","value":"3"},{"label":"PA","value":"11"},{"label":"AVG","value":".100"},{"label":"OBP","value":".182"},{"label":"SLG","value":".200"},{"label":"OPS","value":".382"},{"label":"HR","value":"0"},{"label":"RBI","value":"1"},{"label":"SB","value":"0"}]},{"season":"Jul 2026","team":"Baltimore Orioles","level":"MLB","stats":[{"label":"G","value":"7"},{"label":"PA","value":"18"},{"label":"AVG","value":".250"},{"label":"OBP","value":".333"},{"label":"SLG","value":".313"},{"label":"OPS","value":".646"},{"label":"HR","value":"0"},{"label":"RBI","value":"0"},{"label":"SB","value":"0"}]}]},{"key":"home","label":"Home","seasons":[{"season":"2025","team":"Baltimore Orioles","level":"MLB","stats":[{"label":"G","value":"17"},{"label":"PA","value":"64"},{"label":"AVG","value":".240"},{"label":"OBP","value":".397"},{"label":"SLG","value":".440"},{"label":"OPS","value":".837"},{"label":"HR","value":"2"},{"label":"RBI","value":"6"},{"label":"SB","value":"1"}]},{"season":"2026","team":"Baltimore Orioles","level":"MLB","stats":[{"label":"G","value":"25"},{"label":"PA","value":"84"},{"label":"AVG","value":".240"},{"label":"OBP","value":".313"},{"label":"SLG","value":".387"},{"label":"OPS","value":".700"},{"label":"HR","value":"2"},{"label":"RBI","value":"7"},{"label":"SB","value":"1"}]}],"months":[{"season":"Mar 2026","team":"Baltimore Orioles","level":"MLB","stats":[{"label":"G","value":"3"},{"label":"PA","value":"9"},{"label":"AVG","value":".111"},{"label":"OBP","value":".111"},{"label":"SLG","value":".222"},{"label":"OPS","value":".333"},{"label":"HR","value":"0"},{"label":"RBI","value":"2"},{"label":"SB","value":"0"}]},{"season":"Apr 2026","team":"Baltimore Orioles","level":"MLB","stats":[{"label":"G","value":"11"},{"label":"PA","value":"42"},{"label":"AVG","value":".250"},{"label":"OBP","value":".341"},{"label":"SLG","value":".417"},{"label":"OPS","value":".758"},{"label":"HR","value":"2"},{"label":"RBI","value":"3"},{"label":"SB","value":"1"}]},{"season":"May 2026","team":"Baltimore Orioles","level":"MLB","stats":[{"label":"G","value":"3"},{"label":"PA","value":"9"},{"label":"AVG","value":".375"},{"label":"OBP","value":".444"},{"label":"SLG","value":".625"},{"label":"OPS","value":"1.069"},{"label":"HR","value":"0"},{"label":"RBI","value":"1"},{"label":"SB","value":"0"}]},{"season":"Jun 2026","team":"Baltimore Orioles","level":"MLB","stats":[{"label":"G","value":"3"},{"label":"PA","value":"11"},{"label":"AVG","value":".100"},{"label":"OBP","value":".182"},{"label":"SLG","value":".200"},{"label":"OPS","value":".382"},{"label":"HR","value":"0"},{"label":"RBI","value":"1"},{"label":"SB","value":"0"}]},{"season":"Jul 2026","team":"Baltimore Orioles","level":"MLB","stats":[{"label":"G","value":"5"},{"label":"PA","value":"13"},{"label":"AVG","value":".333"},{"label":"OBP","value":".385"},{"label":"SLG","value":".417"},{"label":"OPS","value":".801"},{"label":"HR","value":"0"},{"label":"RBI","value":"0"},{"label":"SB","value":"0"}]}]},{"key":"away","label":"Away","seasons":[{"season":"2025","team":"Baltimore Orioles","level":"MLB","stats":[{"label":"G","value":"18"},{"label":"PA","value":"73"},{"label":"AVG","value":".217"},{"label":"OBP","value":".356"},{"label":"SLG","value":".367"},{"label":"OPS","value":".723"},{"label":"HR","value":"2"},{"label":"RBI","value":"8"},{"label":"SB","value":"1"}]},{"season":"2026","team":"Baltimore Orioles","level":"MLB","stats":[{"label":"G","value":"18"},{"label":"PA","value":"64"},{"label":"AVG","value":".222"},{"label":"OBP","value":".328"},{"label":"SLG","value":".296"},{"label":"OPS","value":".624"},{"label":"HR","value":"0"},{"label":"RBI","value":"6"},{"label":"SB","value":"2"}]}],"months":[{"season":"Apr 2026","team":"Baltimore Orioles","level":"MLB","stats":[{"label":"G","value":"10"},{"label":"PA","value":"39"},{"label":"AVG","value":".235"},{"label":"OBP","value":".308"},{"label":"SLG","value":".294"},{"label":"OPS","value":".602"},{"label":"HR","value":"0"},{"label":"RBI","value":"4"},{"label":"SB","value":"0"}]},{"season":"May 2026","team":"Baltimore Orioles","level":"MLB","stats":[{"label":"G","value":"6"},{"label":"PA","value":"20"},{"label":"AVG","value":".250"},{"label":"OBP","value":".400"},{"label":"SLG","value":".375"},{"label":"OPS","value":".775"},{"label":"HR","value":"0"},{"label":"RBI","value":"2"},{"label":"SB","value":"2"}]},{"season":"Jul 2026","team":"Baltimore Orioles","level":"MLB","stats":[{"label":"G","value":"2"},{"label":"PA","value":"5"},{"label":"AVG","value":".000"},{"label":"OBP","value":".200"},{"label":"SLG","value":".000"},{"label":"OPS","value":".200"},{"label":"HR","value":"0"},{"label":"RBI","value":"0"},{"label":"SB","value":"0"}]}]},{"key":"day","label":"Day","seasons":[{"season":"2025","team":"Baltimore Orioles","level":"MLB","stats":[{"label":"G","value":"14"},{"label":"PA","value":"56"},{"label":"AVG","value":".196"},{"label":"OBP","value":".339"},{"label":"SLG","value":".326"},{"label":"OPS","value":".665"},{"label":"HR","value":"2"},{"label":"RBI","value":"6"},{"label":"SB","value":"1"}]},{"season":"2026","team":"Baltimore Orioles","level":"MLB","stats":[{"label":"G","value":"21"},{"label":"PA","value":"70"},{"label":"AVG","value":".250"},{"label":"OBP","value":".343"},{"label":"SLG","value":".383"},{"label":"OPS","value":".726"},{"label":"HR","value":"1"},{"label":"RBI","value":"8"},{"label":"SB","value":"2"}]}],"months":[{"season":"Mar 2026","team":"Baltimore Orioles","level":"MLB","stats":[{"label":"G","value":"2"},{"label":"PA","value":"6"},{"label":"AVG","value":".167"},{"label":"OBP","value":".167"},{"label":"SLG","value":".333"},{"label":"OPS","value":".500"},{"label":"HR","value":"0"},{"label":"RBI","value":"2"},{"label":"SB","value":"0"}]},{"season":"Apr 2026","team":"Baltimore Orioles","level":"MLB","stats":[{"label":"G","value":"12"},{"label":"PA","value":"45"},{"label":"AVG","value":".250"},{"label":"OBP","value":".311"},{"label":"SLG","value":".375"},{"label":"OPS","value":".686"},{"label":"HR","value":"1"},{"label":"RBI","value":"5"},{"label":"SB","value":"0"}]},{"season":"May 2026","team":"Baltimore Orioles","level":"MLB","stats":[{"label":"G","value":"3"},{"label":"PA","value":"10"},{"label":"AVG","value":".375"},{"label":"OBP","value":".500"},{"label":"SLG","value":".625"},{"label":"OPS","value":"1.125"},{"label":"HR","value":"0"},{"label":"RBI","value":"1"},{"label":"SB","value":"2"}]},{"season":"Jun 2026","team":"Baltimore Orioles","level":"MLB","stats":[{"label":"G","value":"1"},{"label":"PA","value":"3"},{"label":"AVG","value":".000"},{"label":"OBP","value":".333"},{"label":"SLG","value":".000"},{"label":"OPS","value":".333"},{"label":"HR","value":"0"},{"label":"RBI","value":"0"},{"label":"SB","value":"0"}]},{"season":"Jul 2026","team":"Baltimore Orioles","level":"MLB","stats":[{"label":"G","value":"3"},{"label":"PA","value":"6"},{"label":"AVG","value":".250"},{"label":"OBP","value":".500"},{"label":"SLG","value":".250"},{"label":"OPS","value":".750"},{"label":"HR","value":"0"},{"label":"RBI","value":"0"},{"label":"SB","value":"0"}]}]},{"key":"night","label":"Night","seasons":[{"season":"2025","team":"Baltimore Orioles","level":"MLB","stats":[{"label":"G","value":"21"},{"label":"PA","value":"81"},{"label":"AVG","value":".250"},{"label":"OBP","value":".400"},{"label":"SLG","value":".453"},{"label":"OPS","value":".853"},{"label":"HR","value":"2"},{"label":"RBI","value":"8"},{"label":"SB","value":"1"}]},{"season":"2026","team":"Baltimore Orioles","level":"MLB","stats":[{"label":"G","value":"22"},{"label":"PA","value":"78"},{"label":"AVG","value":".217"},{"label":"OBP","value":".299"},{"label":"SLG","value":".319"},{"label":"OPS","value":".618"},{"label":"HR","value":"1"},{"label":"RBI","value":"5"},{"label":"SB","value":"1"}]}],"months":[{"season":"Mar 2026","team":"Baltimore Orioles","level":"MLB","stats":[{"label":"G","value":"1"},{"label":"PA","value":"3"},{"label":"AVG","value":".000"},{"label":"OBP","value":".000"},{"label":"SLG","value":".000"},{"label":"OPS","value":".000"},{"label":"HR","value":"0"},{"label":"RBI","value":"0"},{"label":"SB","value":"0"}]},{"season":"Apr 2026","team":"Baltimore Orioles","level":"MLB","stats":[{"label":"G","value":"9"},{"label":"PA","value":"36"},{"label":"AVG","value":".233"},{"label":"OBP","value":".343"},{"label":"SLG","value":".333"},{"label":"OPS","value":".676"},{"label":"HR","value":"1"},{"label":"RBI","value":"2"},{"label":"SB","value":"1"}]},{"season":"May 2026","team":"Baltimore Orioles","level":"MLB","stats":[{"label":"G","value":"6"},{"label":"PA","value":"19"},{"label":"AVG","value":".250"},{"label":"OBP","value":".368"},{"label":"SLG","value":".375"},{"label":"OPS","value":".743"},{"label":"HR","value":"0"},{"label":"RBI","value":"2"},{"label":"SB","value":"0"}]},{"season":"Jun 2026","team":"Baltimore Orioles","level":"MLB","stats":[{"label":"G","value":"2"},{"label":"PA","value":"8"},{"label":"AVG","value":".125"},{"label":"OBP","value":".125"},{"label":"SLG","value":".250"},{"label":"OPS","value":".375"},{"label":"HR","value":"0"},{"label":"RBI","value":"1"},{"label":"SB","value":"0"}]},{"season":"Jul 2026","team":"Baltimore Orioles","level":"MLB","stats":[{"label":"G","value":"4"},{"label":"PA","value":"12"},{"label":"AVG","value":".250"},{"label":"OBP","value":".250"},{"label":"SLG","value":".333"},{"label":"OPS","value":".583"},{"label":"HR","value":"0"},{"label":"RBI","value":"0"},{"label":"SB","value":"0"}]}]}],"career":[{"label":"G","value":"78"},{"label":"PA","value":"285"},{"label":"AVG","value":".230"},{"label":"OBP","value":".346"},{"label":"SLG","value":".372"},{"label":"OPS","value":".718"},{"label":"HR","value":"6"},{"label":"RBI","value":"27"},{"label":"SB","value":"5"}]},"sourceLinks":[{"label":"MLB Stats","url":"https://www.mlb.com/player/687637"},{"label":"Baseball Savant","url":"https://baseballsavant.mlb.com/savant-player/dylan-beavers-687637"},{"label":"FanGraphs","url":"https://www.fangraphs.com/players"},{"label":"Baseball Reference","url":"https://www.baseball-reference.com/players/"}]}