{"mlbPlayerId":691026,"playerName":"Masyn Winn","lastUpdated":"2026-07-13T20:28:12.042Z","age":24,"birthPlace":"Katy, TX, USA","preProPath":"Kingwood HS","statGroups":[{"title":"2026 Season Line","source":"MLB Stats API","stats":[{"label":"G","value":"87"},{"label":"PA","value":"357"},{"label":"AVG","value":".243"},{"label":"OBP","value":".314"},{"label":"SLG","value":".331"},{"label":"OPS","value":".645"},{"label":"HR","value":"4"},{"label":"RBI","value":"38"},{"label":"SB","value":"7"}]},{"title":"Career Line","source":"MLB Stats API","stats":[{"label":"G","value":"403"},{"label":"PA","value":"1668"},{"label":"AVG","value":".250"},{"label":"OBP","value":".306"},{"label":"SLG","value":".367"},{"label":"OPS","value":".673"},{"label":"HR","value":"30"},{"label":"RBI","value":"158"},{"label":"SB","value":"29"}]}],"statHistory":{"type":"hitter","source":"MLB Stats API","seasons":[{"season":"2023","team":"St. Louis Cardinals","level":"MLB","stats":[{"label":"G","value":"37"},{"label":"PA","value":"137"},{"label":"AVG","value":".172"},{"label":"OBP","value":".230"},{"label":"SLG","value":".238"},{"label":"OPS","value":".468"},{"label":"HR","value":"2"},{"label":"RBI","value":"12"},{"label":"SB","value":"2"}]},{"season":"2024","team":"St. Louis Cardinals","level":"MLB","stats":[{"label":"G","value":"150"},{"label":"PA","value":"637"},{"label":"AVG","value":".267"},{"label":"OBP","value":".314"},{"label":"SLG","value":".416"},{"label":"OPS","value":".730"},{"label":"HR","value":"15"},{"label":"RBI","value":"57"},{"label":"SB","value":"11"}]},{"season":"2025","team":"St. Louis Cardinals","level":"MLB","stats":[{"label":"G","value":"129"},{"label":"PA","value":"537"},{"label":"AVG","value":".253"},{"label":"OBP","value":".310"},{"label":"SLG","value":".363"},{"label":"OPS","value":".673"},{"label":"HR","value":"9"},{"label":"RBI","value":"51"},{"label":"SB","value":"9"}]},{"season":"2026","team":"St. Louis Cardinals","level":"MLB","stats":[{"label":"G","value":"87"},{"label":"PA","value":"357"},{"label":"AVG","value":".243"},{"label":"OBP","value":".314"},{"label":"SLG","value":".331"},{"label":"OPS","value":".645"},{"label":"HR","value":"4"},{"label":"RBI","value":"38"},{"label":"SB","value":"7"}]}],"months":[{"season":"Mar 2026","team":"St. Louis Cardinals","level":"MLB","stats":[{"label":"G","value":"5"},{"label":"PA","value":"22"},{"label":"AVG","value":".143"},{"label":"OBP","value":".182"},{"label":"SLG","value":".238"},{"label":"OPS","value":".420"},{"label":"HR","value":"0"},{"label":"RBI","value":"0"},{"label":"SB","value":"0"}]},{"season":"Apr 2026","team":"St. Louis Cardinals","level":"MLB","stats":[{"label":"G","value":"21"},{"label":"PA","value":"91"},{"label":"AVG","value":".282"},{"label":"OBP","value":".374"},{"label":"SLG","value":".385"},{"label":"OPS","value":".758"},{"label":"HR","value":"1"},{"label":"RBI","value":"13"},{"label":"SB","value":"4"}]},{"season":"May 2026","team":"St. Louis Cardinals","level":"MLB","stats":[{"label":"G","value":"25"},{"label":"PA","value":"102"},{"label":"AVG","value":".213"},{"label":"OBP","value":".284"},{"label":"SLG","value":".270"},{"label":"OPS","value":".554"},{"label":"HR","value":"0"},{"label":"RBI","value":"7"},{"label":"SB","value":"1"}]},{"season":"Jun 2026","team":"St. Louis Cardinals","level":"MLB","stats":[{"label":"G","value":"23"},{"label":"PA","value":"96"},{"label":"AVG","value":".267"},{"label":"OBP","value":".333"},{"label":"SLG","value":".372"},{"label":"OPS","value":".705"},{"label":"HR","value":"2"},{"label":"RBI","value":"12"},{"label":"SB","value":"2"}]},{"season":"Jul 2026","team":"St. Louis Cardinals","level":"MLB","stats":[{"label":"G","value":"13"},{"label":"PA","value":"46"},{"label":"AVG","value":".233"},{"label":"OBP","value":".283"},{"label":"SLG","value":".326"},{"label":"OPS","value":".608"},{"label":"HR","value":"1"},{"label":"RBI","value":"6"},{"label":"SB","value":"0"}]}],"splitSeries":[{"key":"all","label":"All games","seasons":[{"season":"2023","team":"St. Louis Cardinals","level":"MLB","stats":[{"label":"G","value":"37"},{"label":"PA","value":"137"},{"label":"AVG","value":".172"},{"label":"OBP","value":".230"},{"label":"SLG","value":".238"},{"label":"OPS","value":".468"},{"label":"HR","value":"2"},{"label":"RBI","value":"12"},{"label":"SB","value":"2"}]},{"season":"2024","team":"St. Louis Cardinals","level":"MLB","stats":[{"label":"G","value":"150"},{"label":"PA","value":"637"},{"label":"AVG","value":".267"},{"label":"OBP","value":".314"},{"label":"SLG","value":".416"},{"label":"OPS","value":".730"},{"label":"HR","value":"15"},{"label":"RBI","value":"57"},{"label":"SB","value":"11"}]},{"season":"2025","team":"St. Louis Cardinals","level":"MLB","stats":[{"label":"G","value":"129"},{"label":"PA","value":"537"},{"label":"AVG","value":".253"},{"label":"OBP","value":".310"},{"label":"SLG","value":".363"},{"label":"OPS","value":".673"},{"label":"HR","value":"9"},{"label":"RBI","value":"51"},{"label":"SB","value":"9"}]},{"season":"2026","team":"St. Louis Cardinals","level":"MLB","stats":[{"label":"G","value":"87"},{"label":"PA","value":"357"},{"label":"AVG","value":".243"},{"label":"OBP","value":".314"},{"label":"SLG","value":".331"},{"label":"OPS","value":".645"},{"label":"HR","value":"4"},{"label":"RBI","value":"38"},{"label":"SB","value":"7"}]}],"months":[{"season":"Mar 2026","team":"St. Louis Cardinals","level":"MLB","stats":[{"label":"G","value":"5"},{"label":"PA","value":"22"},{"label":"AVG","value":".143"},{"label":"OBP","value":".182"},{"label":"SLG","value":".238"},{"label":"OPS","value":".420"},{"label":"HR","value":"0"},{"label":"RBI","value":"0"},{"label":"SB","value":"0"}]},{"season":"Apr 2026","team":"St. Louis Cardinals","level":"MLB","stats":[{"label":"G","value":"21"},{"label":"PA","value":"91"},{"label":"AVG","value":".282"},{"label":"OBP","value":".374"},{"label":"SLG","value":".385"},{"label":"OPS","value":".758"},{"label":"HR","value":"1"},{"label":"RBI","value":"13"},{"label":"SB","value":"4"}]},{"season":"May 2026","team":"St. Louis Cardinals","level":"MLB","stats":[{"label":"G","value":"25"},{"label":"PA","value":"102"},{"label":"AVG","value":".213"},{"label":"OBP","value":".284"},{"label":"SLG","value":".270"},{"label":"OPS","value":".554"},{"label":"HR","value":"0"},{"label":"RBI","value":"7"},{"label":"SB","value":"1"}]},{"season":"Jun 2026","team":"St. Louis Cardinals","level":"MLB","stats":[{"label":"G","value":"23"},{"label":"PA","value":"96"},{"label":"AVG","value":".267"},{"label":"OBP","value":".333"},{"label":"SLG","value":".372"},{"label":"OPS","value":".705"},{"label":"HR","value":"2"},{"label":"RBI","value":"12"},{"label":"SB","value":"2"}]},{"season":"Jul 2026","team":"St. Louis Cardinals","level":"MLB","stats":[{"label":"G","value":"13"},{"label":"PA","value":"46"},{"label":"AVG","value":".233"},{"label":"OBP","value":".283"},{"label":"SLG","value":".326"},{"label":"OPS","value":".608"},{"label":"HR","value":"1"},{"label":"RBI","value":"6"},{"label":"SB","value":"0"}]}]},{"key":"home","label":"Home","seasons":[{"season":"2023","team":"St. Louis Cardinals","level":"MLB","stats":[{"label":"G","value":"17"},{"label":"PA","value":"65"},{"label":"AVG","value":".224"},{"label":"OBP","value":".281"},{"label":"SLG","value":".241"},{"label":"OPS","value":".523"},{"label":"HR","value":"0"},{"label":"RBI","value":"3"},{"label":"SB","value":"0"}]},{"season":"2024","team":"St. Louis Cardinals","level":"MLB","stats":[{"label":"G","value":"78"},{"label":"PA","value":"320"},{"label":"AVG","value":".269"},{"label":"OBP","value":".319"},{"label":"SLG","value":".444"},{"label":"OPS","value":".763"},{"label":"HR","value":"10"},{"label":"RBI","value":"27"},{"label":"SB","value":"4"}]},{"season":"2025","team":"St. Louis Cardinals","level":"MLB","stats":[{"label":"G","value":"68"},{"label":"PA","value":"271"},{"label":"AVG","value":".242"},{"label":"OBP","value":".297"},{"label":"SLG","value":".347"},{"label":"OPS","value":".644"},{"label":"HR","value":"3"},{"label":"RBI","value":"26"},{"label":"SB","value":"4"}]},{"season":"2026","team":"St. Louis Cardinals","level":"MLB","stats":[{"label":"G","value":"47"},{"label":"PA","value":"185"},{"label":"AVG","value":".238"},{"label":"OBP","value":".319"},{"label":"SLG","value":".293"},{"label":"OPS","value":".612"},{"label":"HR","value":"1"},{"label":"RBI","value":"14"},{"label":"SB","value":"1"}]}],"months":[{"season":"Mar 2026","team":"St. Louis Cardinals","level":"MLB","stats":[{"label":"G","value":"5"},{"label":"PA","value":"22"},{"label":"AVG","value":".143"},{"label":"OBP","value":".182"},{"label":"SLG","value":".238"},{"label":"OPS","value":".420"},{"label":"HR","value":"0"},{"label":"RBI","value":"0"},{"label":"SB","value":"0"}]},{"season":"Apr 2026","team":"St. Louis Cardinals","level":"MLB","stats":[{"label":"G","value":"8"},{"label":"PA","value":"32"},{"label":"AVG","value":".308"},{"label":"OBP","value":".438"},{"label":"SLG","value":".346"},{"label":"OPS","value":".784"},{"label":"HR","value":"0"},{"label":"RBI","value":"4"},{"label":"SB","value":"1"}]},{"season":"May 2026","team":"St. Louis Cardinals","level":"MLB","stats":[{"label":"G","value":"13"},{"label":"PA","value":"51"},{"label":"AVG","value":".250"},{"label":"OBP","value":".333"},{"label":"SLG","value":".295"},{"label":"OPS","value":".629"},{"label":"HR","value":"0"},{"label":"RBI","value":"4"},{"label":"SB","value":"0"}]},{"season":"Jun 2026","team":"St. Louis Cardinals","level":"MLB","stats":[{"label":"G","value":"13"},{"label":"PA","value":"54"},{"label":"AVG","value":".271"},{"label":"OBP","value":".352"},{"label":"SLG","value":".333"},{"label":"OPS","value":".685"},{"label":"HR","value":"1"},{"label":"RBI","value":"5"},{"label":"SB","value":"0"}]},{"season":"Jul 2026","team":"St. Louis Cardinals","level":"MLB","stats":[{"label":"G","value":"8"},{"label":"PA","value":"26"},{"label":"AVG","value":".160"},{"label":"OBP","value":".192"},{"label":"SLG","value":".200"},{"label":"OPS","value":".392"},{"label":"HR","value":"0"},{"label":"RBI","value":"1"},{"label":"SB","value":"0"}]}]},{"key":"away","label":"Away","seasons":[{"season":"2023","team":"St. Louis Cardinals","level":"MLB","stats":[{"label":"G","value":"20"},{"label":"PA","value":"72"},{"label":"AVG","value":".125"},{"label":"OBP","value":".183"},{"label":"SLG","value":".234"},{"label":"OPS","value":".417"},{"label":"HR","value":"2"},{"label":"RBI","value":"9"},{"label":"SB","value":"2"}]},{"season":"2024","team":"St. Louis Cardinals","level":"MLB","stats":[{"label":"G","value":"72"},{"label":"PA","value":"317"},{"label":"AVG","value":".266"},{"label":"OBP","value":".309"},{"label":"SLG","value":".386"},{"label":"OPS","value":".695"},{"label":"HR","value":"5"},{"label":"RBI","value":"30"},{"label":"SB","value":"7"}]},{"season":"2025","team":"St. Louis Cardinals","level":"MLB","stats":[{"label":"G","value":"61"},{"label":"PA","value":"266"},{"label":"AVG","value":".263"},{"label":"OBP","value":".323"},{"label":"SLG","value":".379"},{"label":"OPS","value":".702"},{"label":"HR","value":"6"},{"label":"RBI","value":"25"},{"label":"SB","value":"5"}]},{"season":"2026","team":"St. Louis Cardinals","level":"MLB","stats":[{"label":"G","value":"40"},{"label":"PA","value":"172"},{"label":"AVG","value":".248"},{"label":"OBP","value":".308"},{"label":"SLG","value":".373"},{"label":"OPS","value":".681"},{"label":"HR","value":"3"},{"label":"RBI","value":"24"},{"label":"SB","value":"6"}]}],"months":[{"season":"Apr 2026","team":"St. Louis Cardinals","level":"MLB","stats":[{"label":"G","value":"13"},{"label":"PA","value":"59"},{"label":"AVG","value":".269"},{"label":"OBP","value":".339"},{"label":"SLG","value":".404"},{"label":"OPS","value":".743"},{"label":"HR","value":"1"},{"label":"RBI","value":"9"},{"label":"SB","value":"3"}]},{"season":"May 2026","team":"St. Louis Cardinals","level":"MLB","stats":[{"label":"G","value":"12"},{"label":"PA","value":"51"},{"label":"AVG","value":".178"},{"label":"OBP","value":".235"},{"label":"SLG","value":".244"},{"label":"OPS","value":".480"},{"label":"HR","value":"0"},{"label":"RBI","value":"3"},{"label":"SB","value":"1"}]},{"season":"Jun 2026","team":"St. Louis Cardinals","level":"MLB","stats":[{"label":"G","value":"10"},{"label":"PA","value":"42"},{"label":"AVG","value":".263"},{"label":"OBP","value":".310"},{"label":"SLG","value":".421"},{"label":"OPS","value":".731"},{"label":"HR","value":"1"},{"label":"RBI","value":"7"},{"label":"SB","value":"2"}]},{"season":"Jul 2026","team":"St. Louis Cardinals","level":"MLB","stats":[{"label":"G","value":"5"},{"label":"PA","value":"20"},{"label":"AVG","value":".333"},{"label":"OBP","value":".400"},{"label":"SLG","value":".500"},{"label":"OPS","value":".900"},{"label":"HR","value":"1"},{"label":"RBI","value":"5"},{"label":"SB","value":"0"}]}]},{"key":"day","label":"Day","seasons":[{"season":"2023","team":"St. Louis Cardinals","level":"MLB","stats":[{"label":"G","value":"9"},{"label":"PA","value":"29"},{"label":"AVG","value":".143"},{"label":"OBP","value":".172"},{"label":"SLG","value":".179"},{"label":"OPS","value":".351"},{"label":"HR","value":"0"},{"label":"RBI","value":"1"},{"label":"SB","value":"1"}]},{"season":"2024","team":"St. Louis Cardinals","level":"MLB","stats":[{"label":"G","value":"63"},{"label":"PA","value":"267"},{"label":"AVG","value":".234"},{"label":"OBP","value":".286"},{"label":"SLG","value":".327"},{"label":"OPS","value":".612"},{"label":"HR","value":"3"},{"label":"RBI","value":"16"},{"label":"SB","value":"1"}]},{"season":"2025","team":"St. Louis Cardinals","level":"MLB","stats":[{"label":"G","value":"52"},{"label":"PA","value":"216"},{"label":"AVG","value":".236"},{"label":"OBP","value":".310"},{"label":"SLG","value":".318"},{"label":"OPS","value":".628"},{"label":"HR","value":"3"},{"label":"RBI","value":"11"},{"label":"SB","value":"4"}]},{"season":"2026","team":"St. Louis Cardinals","level":"MLB","stats":[{"label":"G","value":"33"},{"label":"PA","value":"133"},{"label":"AVG","value":".242"},{"label":"OBP","value":".301"},{"label":"SLG","value":".333"},{"label":"OPS","value":".634"},{"label":"HR","value":"2"},{"label":"RBI","value":"17"},{"label":"SB","value":"2"}]}],"months":[{"season":"Mar 2026","team":"St. Louis Cardinals","level":"MLB","stats":[{"label":"G","value":"3"},{"label":"PA","value":"14"},{"label":"AVG","value":".214"},{"label":"OBP","value":".214"},{"label":"SLG","value":".357"},{"label":"OPS","value":".571"},{"label":"HR","value":"0"},{"label":"RBI","value":"0"},{"label":"SB","value":"0"}]},{"season":"Apr 2026","team":"St. Louis Cardinals","level":"MLB","stats":[{"label":"G","value":"8"},{"label":"PA","value":"36"},{"label":"AVG","value":".257"},{"label":"OBP","value":".278"},{"label":"SLG","value":".286"},{"label":"OPS","value":".563"},{"label":"HR","value":"0"},{"label":"RBI","value":"5"},{"label":"SB","value":"1"}]},{"season":"May 2026","team":"St. Louis Cardinals","level":"MLB","stats":[{"label":"G","value":"11"},{"label":"PA","value":"44"},{"label":"AVG","value":".167"},{"label":"OBP","value":".295"},{"label":"SLG","value":".194"},{"label":"OPS","value":".490"},{"label":"HR","value":"0"},{"label":"RBI","value":"1"},{"label":"SB","value":"1"}]},{"season":"Jun 2026","team":"St. Louis Cardinals","level":"MLB","stats":[{"label":"G","value":"7"},{"label":"PA","value":"27"},{"label":"AVG","value":".292"},{"label":"OBP","value":".333"},{"label":"SLG","value":".458"},{"label":"OPS","value":".792"},{"label":"HR","value":"1"},{"label":"RBI","value":"7"},{"label":"SB","value":"0"}]},{"season":"Jul 2026","team":"St. Louis Cardinals","level":"MLB","stats":[{"label":"G","value":"4"},{"label":"PA","value":"12"},{"label":"AVG","value":".364"},{"label":"OBP","value":".417"},{"label":"SLG","value":".636"},{"label":"OPS","value":"1.053"},{"label":"HR","value":"1"},{"label":"RBI","value":"4"},{"label":"SB","value":"0"}]}]},{"key":"night","label":"Night","seasons":[{"season":"2023","team":"St. Louis Cardinals","level":"MLB","stats":[{"label":"G","value":"28"},{"label":"PA","value":"108"},{"label":"AVG","value":".181"},{"label":"OBP","value":".245"},{"label":"SLG","value":".255"},{"label":"OPS","value":".501"},{"label":"HR","value":"2"},{"label":"RBI","value":"11"},{"label":"SB","value":"1"}]},{"season":"2024","team":"St. Louis Cardinals","level":"MLB","stats":[{"label":"G","value":"87"},{"label":"PA","value":"370"},{"label":"AVG","value":".292"},{"label":"OBP","value":".334"},{"label":"SLG","value":".481"},{"label":"OPS","value":".815"},{"label":"HR","value":"12"},{"label":"RBI","value":"41"},{"label":"SB","value":"10"}]},{"season":"2025","team":"St. Louis Cardinals","level":"MLB","stats":[{"label":"G","value":"77"},{"label":"PA","value":"321"},{"label":"AVG","value":".264"},{"label":"OBP","value":".310"},{"label":"SLG","value":".392"},{"label":"OPS","value":".702"},{"label":"HR","value":"6"},{"label":"RBI","value":"40"},{"label":"SB","value":"5"}]},{"season":"2026","team":"St. Louis Cardinals","level":"MLB","stats":[{"label":"G","value":"54"},{"label":"PA","value":"224"},{"label":"AVG","value":".244"},{"label":"OBP","value":".321"},{"label":"SLG","value":".330"},{"label":"OPS","value":".651"},{"label":"HR","value":"2"},{"label":"RBI","value":"21"},{"label":"SB","value":"5"}]}],"months":[{"season":"Mar 2026","team":"St. Louis Cardinals","level":"MLB","stats":[{"label":"G","value":"2"},{"label":"PA","value":"8"},{"label":"AVG","value":".000"},{"label":"OBP","value":".125"},{"label":"SLG","value":".000"},{"label":"OPS","value":".125"},{"label":"HR","value":"0"},{"label":"RBI","value":"0"},{"label":"SB","value":"0"}]},{"season":"Apr 2026","team":"St. Louis Cardinals","level":"MLB","stats":[{"label":"G","value":"13"},{"label":"PA","value":"55"},{"label":"AVG","value":".302"},{"label":"OBP","value":".436"},{"label":"SLG","value":".465"},{"label":"OPS","value":".901"},{"label":"HR","value":"1"},{"label":"RBI","value":"8"},{"label":"SB","value":"3"}]},{"season":"May 2026","team":"St. Louis Cardinals","level":"MLB","stats":[{"label":"G","value":"14"},{"label":"PA","value":"58"},{"label":"AVG","value":".245"},{"label":"OBP","value":".276"},{"label":"SLG","value":".321"},{"label":"OPS","value":".597"},{"label":"HR","value":"0"},{"label":"RBI","value":"6"},{"label":"SB","value":"0"}]},{"season":"Jun 2026","team":"St. Louis Cardinals","level":"MLB","stats":[{"label":"G","value":"16"},{"label":"PA","value":"69"},{"label":"AVG","value":".258"},{"label":"OBP","value":".333"},{"label":"SLG","value":".339"},{"label":"OPS","value":".672"},{"label":"HR","value":"1"},{"label":"RBI","value":"5"},{"label":"SB","value":"2"}]},{"season":"Jul 2026","team":"St. Louis Cardinals","level":"MLB","stats":[{"label":"G","value":"9"},{"label":"PA","value":"34"},{"label":"AVG","value":".188"},{"label":"OBP","value":".235"},{"label":"SLG","value":".219"},{"label":"OPS","value":".454"},{"label":"HR","value":"0"},{"label":"RBI","value":"2"},{"label":"SB","value":"0"}]}]}],"career":[{"label":"G","value":"403"},{"label":"PA","value":"1668"},{"label":"AVG","value":".250"},{"label":"OBP","value":".306"},{"label":"SLG","value":".367"},{"label":"OPS","value":".673"},{"label":"HR","value":"30"},{"label":"RBI","value":"158"},{"label":"SB","value":"29"}]},"sourceLinks":[{"label":"MLB Stats","url":"https://www.mlb.com/player/691026"},{"label":"Baseball Savant","url":"https://baseballsavant.mlb.com/savant-player/masyn-winn-691026"},{"label":"FanGraphs","url":"https://www.fangraphs.com/players"},{"label":"Baseball Reference","url":"https://www.baseball-reference.com/players/"}]}